{
  "api": {
    "googleImageSearch": {
      "dependsOn": [
        {
          "attributes": [
            "Name",
            "Arn"
          ],
          "category": "function",
          "resourceName": "googleImageSearch"
        }
      ],
      "providerPlugin": "awscloudformation",
      "service": "API Gateway"
    },
    "imageProxy": {
      "dependsOn": [
        {
          "attributes": [
            "Name",
            "Arn"
          ],
          "category": "function",
          "resourceName": "imageProxyFunction"
        }
      ],
      "providerPlugin": "awscloudformation",
      "service": "API Gateway"
    },
    "travellog": {
      "dependsOn": [
        {
          "attributes": [
            "UserPoolId"
          ],
          "category": "auth",
          "resourceName": "travellog44cb0c14"
        }
      ],
      "output": {
        "authConfig": {
          "additionalAuthenticationProviders": [],
          "defaultAuthentication": {
            "authenticationType": "AMAZON_COGNITO_USER_POOLS",
            "userPoolConfig": {
              "userPoolId": "authtravellog44cb0c14"
            }
          }
        }
      },
      "providerPlugin": "awscloudformation",
      "service": "AppSync"
    }
  },
  "auth": {
    "travellog44cb0c14": {
      "customAuth": false,
      "dependsOn": [],
      "frontendAuthConfig": {
        "mfaConfiguration": "OFF",
        "mfaTypes": [
          "SMS"
        ],
        "passwordProtectionSettings": {
          "passwordPolicyCharacters": [],
          "passwordPolicyMinLength": 8
        },
        "signupAttributes": [
          "EMAIL"
        ],
        "socialProviders": [],
        "usernameAttributes": [
          "EMAIL"
        ],
        "verificationMechanisms": [
          "EMAIL"
        ]
      },
      "providerPlugin": "awscloudformation",
      "service": "Cognito"
    }
  },
  "function": {
    "googleImageSearch": {
      "build": true,
      "providerPlugin": "awscloudformation",
      "service": "Lambda"
    },
    "imageProxyFunction": {
      "build": true,
      "dependsOn": [
        {
          "attributes": [
            "BucketName"
          ],
          "category": "storage",
          "resourceName": "travellogdb"
        }
      ],
      "providerPlugin": "awscloudformation",
      "service": "Lambda"
    }
  },
  "parameters": {
    "AMPLIFY_function_googleImageSearch_deploymentBucketName": {
      "usedBy": [
        {
          "category": "function",
          "resourceName": "googleImageSearch"
        }
      ]
    },
    "AMPLIFY_function_googleImageSearch_googleApiKey": {
      "usedBy": [
        {
          "category": "function",
          "resourceName": "googleImageSearch"
        }
      ]
    },
    "AMPLIFY_function_googleImageSearch_googleSearchEngineId": {
      "usedBy": [
        {
          "category": "function",
          "resourceName": "googleImageSearch"
        }
      ]
    },
    "AMPLIFY_function_googleImageSearch_s3Key": {
      "usedBy": [
        {
          "category": "function",
          "resourceName": "googleImageSearch"
        }
      ]
    },
    "AMPLIFY_function_imageProxyFunction_deploymentBucketName": {
      "usedBy": [
        {
          "category": "function",
          "resourceName": "imageProxyFunction"
        }
      ]
    },
    "AMPLIFY_function_imageProxyFunction_s3Key": {
      "usedBy": [
        {
          "category": "function",
          "resourceName": "imageProxyFunction"
        }
      ]
    }
  },
  "storage": {
    "travellogdb": {
      "dependsOn": [],
      "providerPlugin": "awscloudformation",
      "service": "S3"
    }
  }
}